Metadata-Version: 1.1
Name: pyAPIUSBP
Version: 0.1.0
Summary: Using Contec API-USBP functions from Python
Home-page: http://sourceforge.net/p/pyapiusbp/
Author: Hiroyuki Sogo
Author-email: hsogo@ehime-u.ac.jp
License: GNU GPL
Keywords: API-USBP,I/O,Digital Input,Digital Output,USB
Platform: UNKNOWN
Classifier: Development Status :: 3 - Alpha
Classifier: Environment :: Win32 (MS Windows)
Classifier: Intended Audience :: Science/Research
Classifier: License :: OSI Approved :: GNU General Public License (GPL)
Classifier: Operating System :: Microsoft :: Windows
Classifier: Programming Language :: Python
Classifier: Topic :: Scientific/Engineering
